python_csv_json_converter/__init__.py
python_csv_json_converter/converter.py
python_csv_json_converter-0.1.4.dist-info/entry_points.txt
python_csv_json_converter-0.1.4.dist-info/WHEEL
python_csv_json_converter-0.1.4.dist-info/METADATA
python_csv_json_converter-0.1.4.dist-info/RECORD
